AUTHORS
COPYING
ChangeLog
MANIFEST.in
requirements.txt
setup.py
examples/dial_callback_demo.py
examples/dial_polling_demo.py
examples/incoming_call_demo.py
examples/sms_handler_demo.py
examples/ussd_demo.py
gsmmodem/__init__.py
gsmmodem/compat.py
gsmmodem/exceptions.py
gsmmodem/modem.py
gsmmodem/pdu.py
gsmmodem/serial_comms.py
gsmmodem/util.py
python_gsmmodem.egg-info/PKG-INFO
python_gsmmodem.egg-info/SOURCES.txt
python_gsmmodem.egg-info/dependency_links.txt
python_gsmmodem.egg-info/requires.txt
python_gsmmodem.egg-info/top_level.txt
test/test_gsmterm.py
test/test_modem.py
test/test_pdu.py
test/test_serial_comms.py
tools/gsmterm.py
tools/identify-modem.py
tools/sendsms.py
tools/gsmtermlib/__init__.py
tools/gsmtermlib/atcommands.py
tools/gsmtermlib/posoptparse.py
tools/gsmtermlib/terminal.py
tools/gsmtermlib/trie.py